{
  "capturedAt": "2026-06-14T15:19:23.918Z",
  "wallets": [
    "FPa1NnUpG89LpHLnKAPrNrxksVZWrjcpNAqnXiwpoqYn"
  ],
  "totals": {
    "liquidityUsd": 11138.479526202042,
    "earnedUsd": 185.8400204809896,
    "unclaimedFeeUsd": 74.32039902918962,
    "claimedFeeUsd": 111.51962145179999,
    "depositUsd": 11316.028698596756,
    "bonusUsd": 0.3631213888474353,
    "pnlUsd": 8.29094581028229,
    "positionCount": 4,
    "activeCount": 4,
    "inRangeCount": 4,
    "weightedApr": 12.403717773728689,
    "realApr": 19.643205733514748,
    "totalReturnApr": 36.28419141832389
  },
  "positions": [
    {
      "positionAddress": "H4KrpUncp1MbU38eYrUWb15JTHd5HfMrTKrTBnP8mkaX",
      "nftMint": "DXccR1sExHR8KrvQAYYaJiYNwhAhdHeBGWuodhSxoEVz",
      "poolAddress": "FSLSua26xaXSLUG31SnyifgS6wgkRh5SirbCZW9zXNoG",
      "pair": "QQQx/USDC",
      "symbolA": "QQQx",
      "symbolB": "USDC",
      "status": "active",
      "lowerTick": 18250,
      "upperTick": 20260,
      "priceLower": 620.2229077608716,
      "priceUpper": 758.2922707131269,
      "currentPrice": 726.2647470505899,
      "inRange": true,
      "nearestBoundaryPct": 4.409896500222941,
      "distanceToLowerPct": 14.600989476683445,
      "distanceToUpperPct": 4.409896500222941,
      "rangeWidthPct": 19.010885976906387,
      "riskLevel": "medium",
      "liquidityUsd": 4220.8572556413,
      "earnedUsd": 58.8381637218,
      "earnedPct": 1.4211983,
      "unclaimedFeeUsd": 28.2550704232,
      "unclaimedTokens": [
        {
          "symbol": "QQQx",
          "amount": 0.0201677,
          "usd": 14.650018957
        },
        {
          "symbol": "USDC",
          "amount": 13.602331,
          "usd": 13.605051466199999
        }
      ],
      "claimedFeeUsd": 30.5830932986,
      "depositUsd": 4140.038932663977,
      "realApr": 13.088068702605932,
      "totalReturnUsd": 198.49472294214996,
      "totalReturnApr": 44.15352904715213,
      "ageDays": 39.634372210648145,
      "pnlUsd": 139.65655922034995,
      "pnlPct": 3.3733151,
      "apr": 12.5223727,
      "bonusUsd": 0.025243884294920926,
      "poolTvlUsd": 373148.384164142,
      "poolVolume24hUsd": 63759.534333298,
      "poolFeeApr": 12.5223727
    },
    {
      "positionAddress": "G6fzGAjJDegufiiyzHv4nMhqBC6jBGbUijBrXD61veLF",
      "nftMint": "BvBfXC9Y5fcigFrRfba6PekBzfALgapH6b4iijVAyVNh",
      "poolAddress": "6FQQyf7UcyU86TZC1cmAcfC4a18SJyDggEKtQfTJWmfs",
      "pair": "TSLAx/USDC",
      "symbolA": "TSLAx",
      "symbolB": "USDC",
      "status": "active",
      "lowerTick": 12170,
      "upperTick": 16090,
      "priceLower": 337.6835924514526,
      "priceUpper": 499.740888626235,
      "currentPrice": 406.06878624275146,
      "inRange": true,
      "nearestBoundaryPct": 16.8407905527655,
      "distanceToLowerPct": 16.8407905527655,
      "distanceToUpperPct": 23.06803811497236,
      "rangeWidthPct": 39.908828667737865,
      "riskLevel": "low",
      "liquidityUsd": 2981.836416648,
      "earnedUsd": 56.637091300099996,
      "earnedPct": 1.8367718000000002,
      "unclaimedFeeUsd": 20.4254299241,
      "unclaimedTokens": [
        {
          "symbol": "TSLAx",
          "amount": 0.02593709,
          "usd": 10.534349103499999
        },
        {
          "symbol": "USDC",
          "amount": 9.889103,
          "usd": 9.891080820600001
        }
      ],
      "claimedFeeUsd": 36.211661375999995,
      "depositUsd": 3083.5127534599,
      "realApr": 19.768178133450938,
      "totalReturnUsd": 11.597860933126988,
      "totalReturnApr": 4.048028873485617,
      "ageDays": 33.914187025462965,
      "pnlUsd": -45.03923036697301,
      "pnlPct": -1.4606468,
      "apr": 5.6106584,
      "bonusUsd": 0.013938842175,
      "poolTvlUsd": 499113.29008794547,
      "poolVolume24hUsd": 38361.7937339602,
      "poolFeeApr": 5.6106584
    },
    {
      "positionAddress": "3awA2cYUejR12swLtpB6EzyZfTQZ15FT4QEU66DmMhtA",
      "nftMint": "3HhKFLgGPjy4kfCKGXKDjzkQcS9UFaQHRUAR2sYBpTFU",
      "poolAddress": "GjLusGo2z3mnXPmebhhNt9ocMDJgfdxrDFctVF8Ev3Kg",
      "pair": "NVDAx/USDC",
      "symbolA": "NVDAx",
      "symbolB": "USDC",
      "status": "active",
      "lowerTick": 6200,
      "upperTick": 9170,
      "priceLower": 185.8870419811501,
      "priceUpper": 250.16591032367174,
      "currentPrice": 206.82863427314538,
      "inRange": true,
      "nearestBoundaryPct": 10.125093348699027,
      "distanceToLowerPct": 10.125093348699027,
      "distanceToUpperPct": 20.953228358745328,
      "rangeWidthPct": 31.07832170744435,
      "riskLevel": "low",
      "liquidityUsd": 2929.1763018246,
      "earnedUsd": 69.3639014779,
      "earnedPct": 2.2421118,
      "unclaimedFeeUsd": 24.6390347007,
      "unclaimedTokens": [
        {
          "symbol": "NVDAx",
          "amount": 0.06170295,
          "usd": 12.7644892665
        },
        {
          "symbol": "USDC",
          "amount": 11.872171,
          "usd": 11.8745454342
        }
      ],
      "claimedFeeUsd": 44.7248667772,
      "depositUsd": 3093.6861741419,
      "realApr": 26.534337359536014,
      "totalReturnUsd": -25.782061946648,
      "totalReturnApr": -9.862621838461287,
      "ageDays": 30.841953229166666,
      "pnlUsd": -95.145963424548,
      "pnlPct": -3.0754885,
      "apr": 9.3971949,
      "bonusUsd": 0.28427367308,
      "poolTvlUsd": 454418.91545175,
      "poolVolume24hUsd": 58351.579609365,
      "poolFeeApr": 9.3971949
    },
    {
      "positionAddress": "C8kHBWRDnJSwhSorPyFxmvFxvc3rUpJUfWAtcheQVjkF",
      "nftMint": "3qDm5mfXjwwqrJ27Ua3HaAvd7kfHY512nCKoNGTSkuKj",
      "poolAddress": "LVcDubF4BFsEw8qmxupmw74bbZfiya99kor5c3Hh24r",
      "pair": "SPCXx/USDC",
      "symbolA": "SPCXx",
      "symbolB": "USDC",
      "status": "active",
      "lowerTick": 2730,
      "upperTick": 6800,
      "priceLower": 131.3882311404305,
      "priceUpper": 197.38106260019273,
      "currentPrice": 167.09299870258369,
      "inRange": true,
      "nearestBoundaryPct": 18.12647096693748,
      "distanceToLowerPct": 21.3682008458689,
      "distanceToUpperPct": 18.12647096693748,
      "rangeWidthPct": 39.494671812806374,
      "riskLevel": "low",
      "liquidityUsd": 1006.6095520881404,
      "earnedUsd": 1.0008639811896127,
      "earnedPct": 0.1002076,
      "unclaimedFeeUsd": 1.0008639811896127,
      "unclaimedTokens": [
        {
          "symbol": "SPCXx",
          "amount": 0.00290583,
          "usd": 0.4856409571896127
        },
        {
          "symbol": "USDC",
          "amount": 0.51512,
          "usd": 0.515223024
        }
      ],
      "claimedFeeUsd": 0,
      "depositUsd": 998.7908383309782,
      "realApr": 25.083954370479468,
      "totalReturnUsd": 9.82044436264297,
      "totalReturnApr": 246.12293270617806,
      "ageDays": 1.4581337847222222,
      "pnlUsd": 8.819580381453358,
      "pnlPct": 0.8830258000000001,
      "apr": 40.777779800000005,
      "bonusUsd": 0.0396649892975143,
      "poolTvlUsd": 59729.27990045891,
      "poolVolume24hUsd": 66558.8682062066,
      "poolFeeApr": 40.777779800000005
    }
  ],
  "strategy": {
    "lifetimeFeesUsd": 414.9280647356742,
    "lifetimePnlUsd": 255.41244005152504,
    "totalDepositEverUsd": 50019.86577579892,
    "currentDepositUsd": 11316.028698596756,
    "depositYears": 1769.8258680957606,
    "feeApr": 23.444570011970438,
    "totalReturnApr": 37.87607113622146,
    "realizedFeesUsd": 229.08804425468458,
    "unrealizedFeesUsd": 185.8400204809896,
    "closedCount": 16,
    "activeCount": 4,
    "avgHoldDays": 6.829908854166667
  },
  "closedPositions": [
    {
      "positionAddress": "J9LZowMWVtn9RktmH9SNgfbGvsANKjJ9grrwTsWoMWW8",
      "pair": "SPCXx/USDC",
      "depositUsd": 998.951428911829,
      "earnedUsd": 0.19340556724017832,
      "pnlUsd": 0.6207666975557177,
      "ageDays": 0.02042824074074074,
      "openTime": 1781322615000,
      "feeApr": 345.92862131667755,
      "totalReturnApr": 1456.2429256514793
    },
    {
      "positionAddress": "8bBDQZo1qs7hSwUicTWrGBYAvZoinbBTfPP1zUpsN61s",
      "pair": "NVDAx/USDC",
      "depositUsd": 3026.9124545954,
      "earnedUsd": 11.9190697623,
      "pnlUsd": 29.551003567043878,
      "ageDays": 3.0714004629629628,
      "openTime": 1778520249000,
      "feeApr": 46.79494276690871,
      "totalReturnApr": 162.81385600445404
    },
    {
      "positionAddress": "C8XWmWtxuFCg3ZgZx6GiQsugWvgpsN6baP5RfQ2LmUZB",
      "pair": "TSLAx/USDC",
      "depositUsd": 2980.0092639952,
      "earnedUsd": 16.3657695621,
      "pnlUsd": 68.76126368994458,
      "ageDays": 6.169074074074074,
      "openTime": 1777987169000,
      "feeApr": 32.49314114764827,
      "totalReturnApr": 169.01403239508295
    },
    {
      "positionAddress": "36GuYBNqC4sBJXXjGzD1xEQkfo48DKqfarqk51moPYiE",
      "pair": "NVDAx/USDC",
      "depositUsd": 2943.7011958044,
      "earnedUsd": 27.0438606344,
      "pnlUsd": 92.83490692297362,
      "ageDays": 11.127152777777777,
      "openTime": 1777558863000,
      "feeApr": 30.135873096089593,
      "totalReturnApr": 133.58489658201066
    },
    {
      "positionAddress": "53QJGwqwF5jCKbQdAYXwKqDmvrcKHKqs3tuHxt9H8gJD",
      "pair": "NVDAx/USDC",
      "depositUsd": 3099.7540825168,
      "earnedUsd": 10.8880558773,
      "pnlUsd": -167.4619838651048,
      "ageDays": 2.5942939814814814,
      "openTime": 1777334716000,
      "feeApr": 49.41932129214853,
      "totalReturnApr": -710.6665634711873
    },
    {
      "positionAddress": "4tfsDXSZwpstzAPpCVGttvBTfk47rYV8wMEdvxEYEDyX",
      "pair": "TSLAx/USDC",
      "depositUsd": 2909.4588710449,
      "earnedUsd": 26.6554290968,
      "pnlUsd": 75.67709470298331,
      "ageDays": 7.91724537037037,
      "openTime": 1777303119000,
      "feeApr": 42.23691752294829,
      "totalReturnApr": 162.1512207494523
    },
    {
      "positionAddress": "C5Ts8fNdAkdk9WehiDoJuW4zVLyEJAdCfhfnY6hPwNqT",
      "pair": "NVDAx/USDC",
      "depositUsd": 3067.2841811596,
      "earnedUsd": 5.7734481207,
      "pnlUsd": 31.092935735893096,
      "ageDays": 2.7767245370370373,
      "openTime": 1777094807000,
      "feeApr": 24.74237126277031,
      "totalReturnApr": 157.99254404403194
    },
    {
      "positionAddress": "6911L1Sb2htikiG9UKyAEmqu1TbHjN33gNFDZptFED9V",
      "pair": "TSLAx/USDC",
      "depositUsd": 2999.1317455766,
      "earnedUsd": 25.6930060944,
      "pnlUsd": -86.30777011449985,
      "ageDays": 4.6008101851851855,
      "openTime": 1776905609000,
      "feeApr": 67.9638424587811,
      "totalReturnApr": -160.33983168034828
    },
    {
      "positionAddress": "Anys9h2u6gaday3ajnSHJLZ9ZxaP5ZKbqPCwQmm6ohPe",
      "pair": "QQQx/USDC",
      "depositUsd": 4028.6555468202996,
      "earnedUsd": 23.018035579747302,
      "pnlUsd": 78.41311190580176,
      "ageDays": 18.374548611111113,
      "openTime": 1776438392000,
      "feeApr": 11.349698008204397,
      "totalReturnApr": 50.013516079518595
    },
    {
      "positionAddress": "HS1kZdAJ4B16j2GBS1K69d2ibmKRJNoGuAZdWZe6se4V",
      "pair": "TSLAx/USDC",
      "depositUsd": 3088.4255899044,
      "earnedUsd": 29.4289176431,
      "pnlUsd": -67.7867938881797,
      "ageDays": 5.40806712962963,
      "openTime": 1776438352000,
      "feeApr": 64.31139616983378,
      "totalReturnApr": -83.82396543928495
    },
    {
      "positionAddress": "B8PPuZwmr3Mvb9wr3C74fdugimUavzNm9bC7di7z9WFP",
      "pair": "TSLAx/USDC",
      "depositUsd": 1545.1266018028,
      "earnedUsd": 4.7888790125,
      "pnlUsd": 22.493688559624946,
      "ageDays": 0.9818287037037037,
      "openTime": 1776353522000,
      "feeApr": 115.21975179149264,
      "totalReturnApr": 656.4147174505094
    },
    {
      "positionAddress": "8jvMe9XZg2USs4reuBSsZkCEYFwUf4vGapXcxghdoaXs",
      "pair": "NVDAx/USDC",
      "depositUsd": 3040.9210191731,
      "earnedUsd": 18.505303737600002,
      "pnlUsd": 39.164021605426775,
      "ageDays": 9.983923611111111,
      "openTime": 1776232196000,
      "feeApr": 22.247575653245292,
      "totalReturnApr": 69.33161955260077
    },
    {
      "positionAddress": "2E3U8CTeSif7FqxssSbhU3Kq5mQ7rUJyaD2Dn99o9fnQ",
      "pair": "QQQx/USDC",
      "depositUsd": 998.7106270271252,
      "earnedUsd": 2.888862327861621,
      "pnlUsd": 20.104449737331727,
      "ageDays": 9.036365740740742,
      "openTime": 1775657650000,
      "feeApr": 11.68385714867581,
      "totalReturnApr": 92.99528432132043
    },
    {
      "positionAddress": "6584F19ZZ7iw7LbtjydUjWDN56Nu9SCf6yhE1XhfEKfQ",
      "pair": "NVDAx/USDC",
      "depositUsd": 1497.4087434284,
      "earnedUsd": 6.5476481274000005,
      "pnlUsd": 39.41866935216889,
      "ageDays": 7.307245370370371,
      "openTime": 1775600850000,
      "feeApr": 21.84158450722369,
      "totalReturnApr": 153.33401981614213
    },
    {
      "positionAddress": "AibzLWTP5nF2wZmMLsQYsSmUaubF6Et859bHdAnUeH24",
      "pair": "TSLAx/USDC",
      "depositUsd": 1500.7698546715,
      "earnedUsd": 15.7747851127,
      "pnlUsd": 49.384982800735656,
      "ageDays": 8.712060185185186,
      "openTime": 1775600800000,
      "feeApr": 44.0373677304501,
      "totalReturnApr": 181.90198093567653
    },
    {
      "positionAddress": "7VtuNTK1KD7RXQTdag5q1SihCPWx2Ag91ZZuEgbDjFp",
      "pair": "QQQx/USDC",
      "depositUsd": 978.6158707698145,
      "earnedUsd": 3.603567998535471,
      "pnlUsd": 21.161146831543157,
      "ageDays": 11.197372685185185,
      "openTime": 1774690197000,
      "feeApr": 12.003204301324569,
      "totalReturnApr": 82.4893360386939
    }
  ]
}