{
  "updatedAt": "2026-06-17T06:20:12.911Z",
  "pools": [
    {
      "poolAddress": "LVcDubF4BFsEw8qmxupmw74bbZfiya99kor5c3Hh24r",
      "pair": "SPCXx/USDC",
      "symbolA": "SPCXx",
      "symbolB": "USDC",
      "addressA": "Xs3oZwbHvqis4NYcf4YKWmEia2eC84wSiVrcYcTqpH8",
      "tvlUsd": 240281.5731755688,
      "vol24hUsd": 6425612.535129387,
      "feeApr": 964.0994360000001,
      "turnover": 2674.201125874236,
      "sigmaDaily": 0.0318994486629085,
      "annVol": 60.94381109875721,
      "effScore": 15.819480577571893
    },
    {
      "poolAddress": "7mcKEBY6Y8EcCst4u55aNAP84Gn2a2VUGCV1n6AS3KoZ",
      "pair": "SPCX/USDC",
      "symbolA": "SPCX",
      "symbolB": "USDC",
      "addressA": "SPCXxcqXj6e5dJDVNovHN8744zkbhM2bYudU45BimGb",
      "tvlUsd": 439957.88669076655,
      "vol24hUsd": 5528429.369148741,
      "feeApr": 455.65085959999993,
      "turnover": 1256.581490272161,
      "sigmaDaily": 0.032692212582657844,
      "annVol": 62.458384440812864,
      "effScore": 7.295271302314682
    },
    {
      "poolAddress": "81sG64oGK7Z1nhwGRnTNCgJq2zHZL2J14uH29cokUUtn",
      "pair": "WLFI/USDC",
      "symbolA": "WLFI",
      "symbolB": "USDC",
      "addressA": "WLFinEv6ypjkczcS83FZqFpgFZYwQXutRbxGe7oC16g",
      "tvlUsd": 257777.21472883862,
      "vol24hUsd": 295182.4334690284,
      "feeApr": 209.5774318,
      "turnover": 114.51067689575942,
      "sigmaDaily": 0.031539366728894125,
      "annVol": 60.255875529758995,
      "effScore": 3.4781244145476653
    },
    {
      "poolAddress": "DyzGYEhdgSn5EEUt4XXviavZ7v7SV2YGrYV8HX3Aw5XT",
      "pair": "SOL/USD1",
      "symbolA": "SOL",
      "symbolB": "USD1",
      "addressA": "So11111111111111111111111111111111111111112",
      "tvlUsd": 259830.66232814023,
      "vol24hUsd": 430132.6392828599,
      "feeApr": 151.1966347,
      "turnover": 165.54344873263852,
      "sigmaDaily": 0.03404389099253288,
      "annVol": 65.04076241693998,
      "effScore": 2.3246442551020983
    },
    {
      "poolAddress": "4k43WcUS8kPXkmL7PhgpwCteYYaSgzXvfKU63FEE1WS5",
      "pair": "GOOGLx/USDC",
      "symbolA": "GOOGLx",
      "symbolB": "USDC",
      "addressA": "XsCPL9dNWBMvFtTmwcCA5v3xWPSMEBCszbQdiLLq6aN",
      "tvlUsd": 367260.434354335,
      "vol24hUsd": 231300.87057276,
      "feeApr": 46.2856072,
      "turnover": 62.98006780376445,
      "sigmaDaily": 0.014192516755024373,
      "annVol": 27.114765188398987,
      "effScore": 1.7070259276965167
    },
    {
      "poolAddress": "6FQQyf7UcyU86TZC1cmAcfC4a18SJyDggEKtQfTJWmfs",
      "pair": "TSLAx/USDC",
      "symbolA": "TSLAx",
      "symbolB": "USDC",
      "addressA": "XsDoVfqeBukxuZHWhdvWHBhgEHjGNst4MLodqsJHzoB",
      "tvlUsd": 482734.67020433454,
      "vol24hUsd": 359442.783677614,
      "feeApr": 54.2210229,
      "turnover": 74.45969926408374,
      "sigmaDaily": 0.02353158372243821,
      "annVol": 44.957027577169,
      "effScore": 1.2060633414192987
    },
    {
      "poolAddress": "DF5SshvX3XTKcvJNxi384FYvfeog7ih9kb89hGbaQBpA",
      "pair": "HYPE/USDC",
      "symbolA": "HYPE",
      "symbolB": "USDC",
      "addressA": "98sMhvDwXj1RQi5c5Mndm3vPe9cBqPrbLaufMXFNMh5g",
      "tvlUsd": 211800.9292411149,
      "vol24hUsd": 309269.8504519352,
      "feeApr": 133.1713427,
      "turnover": 146.019118782931,
      "sigmaDaily": 0.06674463579750657,
      "annVol": 127.51544764559921,
      "effScore": 1.0443545872976903
    },
    {
      "poolAddress": "EHdow7Yhmr1ac8Qff9Co1LhSosr38puA6zLd4cbJLdpV",
      "pair": "AAPLx/USDC",
      "symbolA": "AAPLx",
      "symbolB": "USDC",
      "addressA": "XsbEhLAtcf6HdfpFZ5xEMdqW8nfAvcsP5bdudRLJzJp",
      "tvlUsd": 41573.4944393028,
      "vol24hUsd": 12063.709792098,
      "feeApr": 21.2609184,
      "turnover": 29.017791154676658,
      "sigmaDaily": 0.012558257343402757,
      "annVol": 23.99251696647148,
      "effScore": 0.8861478947669904
    },
    {
      "poolAddress": "9GTj99g9tbz9U6UYDsX6YeRTgUnkYG6GTnHv3qLa5aXq",
      "pair": "SOL/USDC",
      "symbolA": "SOL",
      "symbolB": "USDC",
      "addressA": "So11111111111111111111111111111111111111112",
      "tvlUsd": 49174.36956315248,
      "vol24hUsd": 182436.1842628072,
      "feeApr": 54.115625,
      "turnover": 370.9985219607389,
      "sigmaDaily": 0.03366942129067095,
      "annVol": 64.32533905606486,
      "effScore": 0.8412800584359726
    },
    {
      "poolAddress": "3Z4H4H9bCcLyt1MmK44J5KZWkJ7taiU821QDTVZYaCpz",
      "pair": "HOODx/USDC",
      "symbolA": "HOODx",
      "symbolB": "USDC",
      "addressA": "XsvNBAYkrDRNhA7wPHQfX3ZUXZyZLdnCQDfHZ56bzpg",
      "tvlUsd": 93559.00385785448,
      "vol24hUsd": 84930.4448328919,
      "feeApr": 66.2219806,
      "turnover": 90.77741460557652,
      "sigmaDaily": 0.044263765881240896,
      "annVol": 84.56580597653502,
      "effScore": 0.7830822379718702
    },
    {
      "poolAddress": "DmHek82VP6HtBmSz56wDrfr4nJysmtGQhpY7D5HVkGnX",
      "pair": "MSTRx/USDC",
      "symbolA": "MSTRx",
      "symbolB": "USDC",
      "addressA": "XsP7xzNPvEHS1m6qfanPUGjNmdnmsLKEoNAnHjdxxyZ",
      "tvlUsd": 141944.68230670577,
      "vol24hUsd": 113530.7840944158,
      "feeApr": 57.8469256,
      "turnover": 79.98241445150099,
      "sigmaDaily": 0.0415301848575974,
      "annVol": 79.34330676382018,
      "effScore": 0.7290712721640392
    },
    {
      "poolAddress": "BqXGCG4vcD81GMiX2Rw9sKrSTqeAAZS6mGR5Ek69B7Lm",
      "pair": "METAx/USDC",
      "symbolA": "METAx",
      "symbolB": "USDC",
      "addressA": "Xsa62P5mvPszXL1krVUnU5ar38bBSVcWAB6fmPCo5Zu",
      "tvlUsd": 73279.3169202416,
      "vol24hUsd": 26893.5940780456,
      "feeApr": 26.835145599999997,
      "turnover": 36.700115678366686,
      "sigmaDaily": 0.019495095714482946,
      "annVol": 37.2453280660341,
      "effScore": 0.7204969587708459
    },
    {
      "poolAddress": "5pobXosbeGSCRG3HdaRiw2TaihDDQMXkHFVbUTF24weM",
      "pair": "COINx/USDC",
      "symbolA": "COINx",
      "symbolB": "USDC",
      "addressA": "Xs7ZdzSHLU9ftNJsii5fCeJhoRWSC32SQGzGQtePxNu",
      "tvlUsd": 128668.47068304959,
      "vol24hUsd": 71333.9524423748,
      "feeApr": 40.5410058,
      "turnover": 55.440118362868,
      "sigmaDaily": 0.03379345649087338,
      "annVol": 64.56230797332152,
      "effScore": 0.6279361298042874
    },
    {
      "poolAddress": "FSLSua26xaXSLUG31SnyifgS6wgkRh5SirbCZW9zXNoG",
      "pair": "QQQx/USDC",
      "symbolA": "QQQx",
      "symbolB": "USDC",
      "addressA": "Xs8S1uUs1zvS2p7iwtsG3b6fkhpvmwz4GYU3gWAmWHZ",
      "tvlUsd": 375387.2886364668,
      "vol24hUsd": 88336.8704540114,
      "feeApr": 17.141891,
      "turnover": 23.53219544936663,
      "sigmaDaily": 0.014822844731329617,
      "annVol": 28.319005096246542,
      "effScore": 0.6053140264546942
    },
    {
      "poolAddress": "CcPxuvtqXeefgnBnCKSKSLvdGdJ3kbWyb3LDevGX3PJg",
      "pair": "MCDx/USDC",
      "symbolA": "MCDx",
      "symbolB": "USDC",
      "addressA": "XsqE9cRRpzxcGKDXj1BJ7Xmg4GRhZoyY1KpmGSxAWT2",
      "tvlUsd": 46635.364171590794,
      "vol24hUsd": 5705.0275491002,
      "feeApr": 8.889992600000001,
      "turnover": 12.233264713252897,
      "sigmaDaily": 0.009758094181852903,
      "annVol": 18.642812757896188,
      "effScore": 0.4768589759200705
    },
    {
      "poolAddress": "GjLusGo2z3mnXPmebhhNt9ocMDJgfdxrDFctVF8Ev3Kg",
      "pair": "NVDAx/USDC",
      "symbolA": "NVDAx",
      "symbolB": "USDC",
      "addressA": "Xsc9qvGR1efVDFGLrVsmkzv3qi45LTBjeUKSPmx9qEh",
      "tvlUsd": 438817.876506285,
      "vol24hUsd": 103334.6022055052,
      "feeApr": 17.174539799999998,
      "turnover": 23.54840304780181,
      "sigmaDaily": 0.020110436911807705,
      "annVol": 38.42093577284215,
      "effScore": 0.4470099297305462
    },
    {
      "poolAddress": "EUAa7W7omZMN6mzLFidmULMYwJBFxfUzE3kD8ywX9Qq9",
      "pair": "XAUt0/USDT",
      "symbolA": "XAUt0",
      "symbolB": "USDT",
      "addressA": "AymATz4TCL9sWNEEV9Kvyz45CHVhDZ6kUgjTJPzLpU9P",
      "tvlUsd": 270370.32109593553,
      "vol24hUsd": 153331.39981,
      "feeApr": 6.354720299999999,
      "turnover": 56.71162396393109,
      "sigmaDaily": 0.014526747442455384,
      "annVol": 27.75331202014683,
      "effScore": 0.2289716014934343
    },
    {
      "poolAddress": "9KWAAyaYF7nmMWzirnBmVhE1q4YXPHcXjzfi6YreNtDY",
      "pair": "XAUt0/USDT",
      "symbolA": "XAUt0",
      "symbolB": "USDT",
      "addressA": "AymATz4TCL9sWNEEV9Kvyz45CHVhDZ6kUgjTJPzLpU9P",
      "tvlUsd": 685485.7181344558,
      "vol24hUsd": 54308.621189,
      "feeApr": 5.7897472,
      "turnover": 7.9226480949596585,
      "sigmaDaily": 0.014422630545453594,
      "annVol": 27.55439696772325,
      "effScore": 0.21012062818075863
    },
    {
      "poolAddress": "Hv44BZaqT5URrrAtGk6jvfbWKL2PytWA4ur2r1QnvtQa",
      "pair": "CRCLx/USDC",
      "symbolA": "CRCLx",
      "symbolB": "USDC",
      "addressA": "XsueG8BtpquVJX9LVLLEGuViXUungE6WmK5YZ3p3bd1",
      "tvlUsd": 1341250.943391642,
      "vol24hUsd": 346646.2760482964,
      "feeApr": 18.7331704,
      "turnover": 25.844997743056688,
      "sigmaDaily": 0.04870328271143318,
      "annVol": 93.0474909714105,
      "effScore": 0.20132912993597968
    },
    {
      "poolAddress": "HGxMfonx2vMRGVpHNvj6JbVM5JUjN8xYFS1UGXMYeaAo",
      "pair": "WETH/USDC",
      "symbolA": "WETH",
      "symbolB": "USDC",
      "addressA": "7vfCXTUXx5WJV5JADk17DUJ4ksgau7utNKj4b963voxs",
      "tvlUsd": 133235.39960868564,
      "vol24hUsd": 45099.1907296789,
      "feeApr": 12.370359,
      "turnover": 33.84925542471137,
      "sigmaDaily": 0.03275664055153624,
      "annVol": 62.58147390252407,
      "effScore": 0.19766806737834075
    },
    {
      "poolAddress": "GLRVQnxhLDPefMgEKvfdbP863gBNPKib8jtFNgF853xu",
      "pair": "BLEND/USDC",
      "symbolA": "BLEND",
      "symbolB": "USDC",
      "addressA": "BWsnyEa1XtsNRdgPaDoA1WVUonF7BBGZTd2zc72NQsWT",
      "tvlUsd": 61007.1945014492,
      "vol24hUsd": 15337.7220858613,
      "feeApr": 22.786795700000003,
      "turnover": 25.14084152074385,
      "sigmaDaily": 0.06591101959905513,
      "annVol": 125.9228261346713,
      "effScore": 0.18095842032349319
    },
    {
      "poolAddress": "HDQqC3z3kncjdeyrCBM6v8VE1mbPcn2xbDmWNXzBBKJC",
      "pair": "JLP/USDC",
      "symbolA": "JLP",
      "symbolB": "USDC",
      "addressA": "27G8MtK7VtTcCHkpASjSDdkWWYfoqT6ggEuKidVJidD4",
      "tvlUsd": 30782.065366871895,
      "vol24hUsd": 13063.9388606878,
      "feeApr": 6.2006116,
      "turnover": 42.440098495624014,
      "sigmaDaily": 0.0202503220266642,
      "annVol": 38.68818590952727,
      "effScore": 0.16027144861483544
    },
    {
      "poolAddress": "8HPQzqMDoDcRDMh3Si75EGWh276QbcVrfHvrNFVPnW8s",
      "pair": "MNT/USDC",
      "symbolA": "MNT",
      "symbolB": "USDC",
      "addressA": "4SoQ8UkWfeDH47T56PA53CZCeW4KytYCiU65CwBWoJUt",
      "tvlUsd": 947400.9702174509,
      "vol24hUsd": 94854.2910004828,
      "feeApr": 11.0254885,
      "turnover": 10.01205339474283,
      "sigmaDaily": 0.03611969805636807,
      "annVol": 69.00658624394977,
      "effScore": 0.15977443748663442
    },
    {
      "poolAddress": "H5zhyinHqif8sL6fkSKyYei1Qjuw2kcK9tN4EtxrcvfN",
      "pair": "SKR/USDC",
      "symbolA": "SKR",
      "symbolB": "USDC",
      "addressA": "SKRbvo6Gf7GondiT3BbTfuRDPqLWei4j2Qy2NPGZhW3",
      "tvlUsd": 305506.4032430876,
      "vol24hUsd": 26350.8973151842,
      "feeApr": 7.8642226,
      "turnover": 8.625317517229622,
      "sigmaDaily": 0.04799205204174468,
      "annVol": 91.6886866848794,
      "effScore": 0.08577091552230628
    }
  ]
}